llm_git_commits/__init__.py
llm_git_commits/main.py
llm_git_commits-1.1.1.dist-info/licenses/LICENSE
llm_git_commits-1.1.1.dist-info/METADATA
llm_git_commits-1.1.1.dist-info/WHEEL
llm_git_commits-1.1.1.dist-info/entry_points.txt
llm_git_commits-1.1.1.dist-info/top_level.txt
llm_git_commits-1.1.1.dist-info/RECORD
