Metadata-Version: 2.4
Name: llm-git-commits
Version: 1.1.1
Summary: Intelligent Git Commit Tool with LLM Integration
Home-page: https://github.com/Slipstreamm/llm-git-commits
Author: Slipstream
Author-email: me@slipstreamm.dev
Classifier: Programming Language :: Python :: 3
Classifier: License :: OSI Approved :: MIT License
Classifier: Operating System :: OS Independent
Requires-Python: >=3.10
License-File: LICENSE
Requires-Dist: requests
Dynamic: author
Dynamic: author-email
Dynamic: classifier
Dynamic: description
Dynamic: description-content-type
Dynamic: home-page
Dynamic: license-file
Dynamic: requires-dist
Dynamic: requires-python
Dynamic: summary
